thepeer/__init__.py
thepeer/_base.py
thepeer/clients/__init__.py
thepeer/clients/links.py
thepeer/clients/transactions.py
thepeer/clients/users.py
thepeer/thepeer.py
thepeer/utils.py
thepeer-0.1.0.dist-info/LICENSE
thepeer-0.1.0.dist-info/METADATA
thepeer-0.1.0.dist-info/WHEEL
thepeer-0.1.0.dist-info/RECORD
