Metadata-Version: 2.1
Name: thepeer
Version: 0.1.0
Summary: A 3rd party developer friendly client package for thepeer
Home-page: https://github.com/gray-adeyi/thepeer
License: MIT
Keywords: thepeer,api wrapper
Author: Gbenga Adeyi
Author-email: adeyigbenga005@gmail.com
Maintainer: Gbenga Adeyi
Maintainer-email: adeyigbenga005@gmail.com
Requires-Python: >=3.9,<4.0
Classifier: Intended Audience :: Developers
Classifier: License :: OSI Approved :: MIT License
Classifier: Programming Language :: Python :: 3
Classifier: Programming Language :: Python :: 3.9
Classifier: Programming Language :: Python :: 3.10
Classifier: Programming Language :: Python :: 3.11
Requires-Dist: httpx (>=0.24.1,<0.25.0)
Project-URL: Repository, https://github.com/gray-adeyi/thepeer
